rizzler/__init__.py
rizzler/commands/__init__.py
rizzler/commands/build.py
rizzler/commands/clean.py
rizzler/commands/initiate.py
rizzler/configs.py
rizzler/core.py
rizzler/load_config.py
rizzler/rizzler_config.py
rizzler/script.yaml
rizzler/templates.yaml
rizzler/templating/__init__.py
rizzler/templating/rizzle_templates.py
rizzler/types/__init__.py
rizzler/types/mutex_option.py
rizzler-0.1.9.dist-info/LICENSE
rizzler-0.1.9.dist-info/METADATA
rizzler-0.1.9.dist-info/WHEEL
rizzler-0.1.9.dist-info/entry_points.txt
rizzler-0.1.9.dist-info/RECORD
