Metadata-Version: 2.1
Name: rizzler
Version: 0.1.9
Summary: Rizzler creates a parallel front-end dev-server using ViteJS for ASGI Frameworks
Home-page: https://github.com/aekasitt/rizzler
License: MIT
Keywords: asgi,blacksheep,fastapi,hmr,javascript,litestar,node,npm,pnpm,quart,sanic,starlette,uvicorn,vite
Author: Sitt Guruvanich
Author-email: aekazitt+github@gmail.com
Requires-Python: >=3.9,<4.0
Classifier: Development Status :: 3 - Alpha
Classifier: Environment :: Web Environment
Classifier: Framework :: AsyncIO
Classifier: Intended Audience :: Developers
Classifier: License :: OSI Approved :: MIT License
Classifier: Operating System :: OS Independent
Classifier: Programming Language :: Python
Classifier: Programming Language :: Python :: 3
Classifier: Programming Language :: Python :: 3.9
Classifier: Programming Language :: Python :: 3.10
Classifier: Programming Language :: Python :: 3.11
Classifier: Programming Language :: Python :: 3.12
Classifier: Programming Language :: Python :: 3 :: Only
Classifier: Topic :: Internet :: WWW/HTTP :: Dynamic Content
Classifier: Topic :: Text Processing :: Markup :: HTML
Classifier: Typing :: Typed
Requires-Dist: click (>=8.1.7,<9.0.0)
Requires-Dist: jinja2 (>=3.1.4,<4.0.0)
Requires-Dist: markupsafe (>=2.1.5,<3.0.0)
Requires-Dist: pydantic (>=2.6.2,<3.0.0)
Requires-Dist: pyyaml (>=6.0.1,<7.0.0)
Requires-Dist: rich (>=13.7.1,<14.0.0)
Requires-Dist: starlette (>=0,<1)
Requires-Dist: tree-sitter (>=0.22.3,<0.23.0)
Requires-Dist: tree-sitter-html (>=0.20.3,<0.21.0)
Requires-Dist: tree-sitter-javascript (>=0.21.4,<0.22.0)
Project-URL: Repository, https://github.com/aekasitt/rizzler
